api_json_cleaner/__init__.py
api_json_cleaner/cleaner.py
api_json_cleaner/cli.py
api_json_cleaner-0.1.0.1.dist-info/licenses/LICENSE
api_json_cleaner-0.1.0.1.dist-info/METADATA
api_json_cleaner-0.1.0.1.dist-info/WHEEL
api_json_cleaner-0.1.0.1.dist-info/entry_points.txt
api_json_cleaner-0.1.0.1.dist-info/top_level.txt
api_json_cleaner-0.1.0.1.dist-info/RECORD
