Metadata-Version: 2.4
Name: api-json-cleaner
Version: 0.1.0.1
Summary: APIレスポンスの"汚い"JSONをキレイにして安全にパース・保存するためのPythonライブラリ
Author-email: Your Name <you@example.com>
License: MIT
Project-URL: Homepage, https://github.com/hayashikunita/api-json-cleaner
Project-URL: Repository, https://github.com/hayashikunita/api-json-cleaner
Project-URL: Issues, https://github.com/hayashikunita/api-json-cleaner/issues
Keywords: json,api,clean,sanitize,mojibake,encoding,japanese
Classifier: Programming Language :: Python :: 3
Classifier: License :: OSI Approved :: MIT License
Classifier: Operating System :: OS Independent
Classifier: Topic :: Software Development :: Libraries :: Python Modules
Classifier: Topic :: Text Processing :: Linguistic
Requires-Python: >=3.9
License-File: LICENSE
Requires-Dist: charset-normalizer>=3.3
Requires-Dist: json5>=0.9
Dynamic: license-file
